pytest_langchain/__init__.py
pytest_langchain/__main__.py
pytest_langchain/plugin.py
pytest_langchain/tests/conftest.py
pytest_langchain/tests/test_chain.py
pytest_langchain-0.1.0.dist-info/LICENSE
pytest_langchain-0.1.0.dist-info/METADATA
pytest_langchain-0.1.0.dist-info/WHEEL
pytest_langchain-0.1.0.dist-info/entry_points.txt
pytest_langchain-0.1.0.dist-info/top_level.txt
pytest_langchain-0.1.0.dist-info/RECORD
