Metadata-Version: 2.1
Name: pytest-langchain
Version: 0.1.0
Summary: Pytest-style test runner for langchain agents
Home-page: https://github.com/ajndkr/pytest-langchain
Author: Ajinkya Indulkar
Author-email: 26824103+ajndkr@users.noreply.github.com
License: MIT License
Classifier: Programming Language :: Python :: 3
Classifier: License :: OSI Approved :: MIT License
Classifier: Operating System :: OS Independent
Requires-Python: <3.11,>=3.7
License-File: LICENSE
Requires-Dist: click
Requires-Dist: pytest
Requires-Dist: PyYAML
Requires-Dist: langchain
